promptvc/__init__.py
promptvc/cli.py
promptvc/config.py
promptvc/diff.py
promptvc/llm.py
promptvc/pipeline.py
promptvc/repo.py
promptvc-0.0.1.dist-info/METADATA
promptvc-0.0.1.dist-info/WHEEL
promptvc-0.0.1.dist-info/entry_points.txt
promptvc-0.0.1.dist-info/top_level.txt
promptvc-0.0.1.dist-info/RECORD
