Metadata-Version: 2.4
Name: promptvc
Version: 0.0.1
Summary: A Git-like version controller for LLM prompts
Home-page: https://github.com/duriantaco/promptvc
Author: oha
Author-email: aaronoh2015@gmail.com
Classifier: Programming Language :: Python :: 3
Classifier: License :: OSI Approved :: Apache Software License
Requires-Dist: typer
Requires-Dist: ruamel.yaml
Requires-Dist: sentence-transformers
Requires-Dist: openai
Requires-Dist: anthropic
Dynamic: author
Dynamic: author-email
Dynamic: classifier
Dynamic: description
Dynamic: description-content-type
Dynamic: home-page
Dynamic: requires-dist
Dynamic: summary
